{"files":{"apps/web/dist/assets":{"size":0,"mtime_nanos":0,"mode":0,"is_dir":true},"apps/web/dist/assets/index-BYTDeAez.js":{"size":247760,"mtime_nanos":1782067056184135500,"mode":420,"is_dir":false},"apps/web/dist/assets/index-Dic6gDbw.css":{"size":45379,"mtime_nanos":1782067056184135500,"mode":420,"is_dir":false},"apps/web/dist/index.html":{"size":759,"mtime_nanos":1782067056183618400,"mode":420,"is_dir":false},"apps/web/.turbo/turbo-build.log":{"size":578,"mtime_nanos":1782067056257147500,"mode":420,"is_dir":false},"apps/web/dist":{"size":0,"mtime_nanos":0,"mode":0,"is_dir":true}},"order":["apps/web/.turbo/turbo-build.log","apps/web/dist","apps/web/dist/assets","apps/web/dist/assets/index-BYTDeAez.js","apps/web/dist/assets/index-Dic6gDbw.css","apps/web/dist/index.html"]}